unikan/__init__.py
unikan/basis.py
unikan/skan.py
unikan/universal_KAN.py
unikan-0.2.5.dist-info/LICENSE
unikan-0.2.5.dist-info/METADATA
unikan-0.2.5.dist-info/WHEEL
unikan-0.2.5.dist-info/top_level.txt
unikan-0.2.5.dist-info/RECORD
