Metadata-Version: 2.1
Name: unikan
Version: 0.2.5
Summary: A Python library based on pytorch for universally building KAN-type networks
Home-page: https://github.com/chikkkit/uni-kan
Author: Zhijie Chen
Author-email: zhijiechencs@gmail.com
Classifier: Programming Language :: Python :: 3
Classifier: License :: OSI Approved :: MIT License
Classifier: Operating System :: OS Independent
Requires-Python: >=3.6
License-File: LICENSE
